{
    "@class": "com.kony.gen.viz.model.component.KVizUserWidget",
    "DNDConfig": null,
    "_children_": [],
    "_height_": {
        "type": "string",
        "value": "65dp"
    },
    "_left_": {
        "type": "string",
        "value": "0dp"
    },
    "_margin_": [
        0,
        0,
        0,
        0
    ],
    "_orientation_": 1,
    "_padding_": [
        0,
        0,
        0,
        0
    ],
    "_percent_": true,
    "_skin_": "s7f98debbd484f2ebbaf46055bd8c952",
    "_top_": {
        "type": "string",
        "value": "0dp"
    },
    "_width_": {
        "type": "string",
        "value": "100%"
    },
    "canUpdateUI": true,
    "containerweight": 0,
    "data": {},
    "id": "CopyChallengesListRow0f387af8879534e",
    "info": null,
    "iscustomlayout": false,
    "isvisible": true,
    "kuid": "bb3a10f54d224dca8b8cfc062165ac7a",
    "masterType": 1,
    "name": "kony.ui.UserWidgetInstance",
    "parent": "flxChallengesList",
    "pf": "userwidgetmodel",
    "retaincontentalignment": false,
    "retainflexpositionproperties": false,
    "retainflowhorizontalalignment": false,
    "sourceUserWidget": "fd636c2575784c1781e2f56b36fc1f4f",
    "wType": "UserWidgetInstance",
    "zindex": 1
}